datasets_server_py/__init__.py
datasets_server_py/datasets_server_service.py
datasets_server_python-0.5.0.dist-info/METADATA
datasets_server_python-0.5.0.dist-info/WHEEL
datasets_server_python-0.5.0.dist-info/top_level.txt
datasets_server_python-0.5.0.dist-info/RECORD
