Metadata-Version: 2.1
Name: datasets-server-python
Version: 0.5.0
Summary: Python SDK to access the Datasets Server
Home-page: UNKNOWN
Author: Nusret Ozates
License: MIT
Keywords: datasets,huggingface
Platform: UNKNOWN
Requires-Dist: requests
Requires-Dist: pydantic
